enchanter/__init__.py
enchanter/addons/__init__.py
enchanter/addons/activation.py
enchanter/addons/criterions/__init__.py
enchanter/addons/criterions/ts_triplet_loss.py
enchanter/addons/layers/__init__.py
enchanter/addons/layers/conv.py
enchanter/addons/layers/dense_interpolation.py
enchanter/addons/layers/mlp.py
enchanter/addons/layers/positional_encoding.py
enchanter/addons/layers/se_layer.py
enchanter/addons/optim_wrapper.py
enchanter/callbacks/__init__.py
enchanter/callbacks/base.py
enchanter/callbacks/early_stopping.py
enchanter/callbacks/loggers.py
enchanter/callbacks/manager.py
enchanter/engine/__init__.py
enchanter/engine/modules.py
enchanter/engine/runner.py
enchanter/engine/saving.py
enchanter/engine/typehint.py
enchanter/metrics/__init__.py
enchanter/metrics/classification.py
enchanter/preprocessing/__init__.py
enchanter/preprocessing/signal/__init__.py
enchanter/preprocessing/signal/functions.py
enchanter/preprocessing/signal/transforms.py
enchanter/tasks/__init__.py
enchanter/tasks/classification.py
enchanter/tasks/ensemble.py
enchanter/tasks/regression.py
enchanter/tasks/ts_unsupervised.py
enchanter/utils/__init__.py
enchanter/utils/backend.py
enchanter/utils/comet.py
enchanter/utils/datasets.py
enchanter/utils/visualize.py
enchanter-0.9.0.dist-info/LICENSE
enchanter-0.9.0.dist-info/WHEEL
enchanter-0.9.0.dist-info/METADATA
enchanter-0.9.0.dist-info/RECORD
