Metadata-Version: 2.1
Name: enchanter
Version: 0.9.0
Summary: Enchanter is a library for machine learning tasks for comet.ml users.
Home-page: https://enchanter.readthedocs.io/
License: Apache-2.0
Keywords: pytorch,comet_ml
Author: Hirotaka Kawashima
Author-email: khirotaka@vivaldi.net
Requires-Python: >=3.7,<4.0
Classifier: License :: OSI Approved :: Apache Software License
Classifier: Operating System :: MacOS :: MacOS X
Classifier: Operating System :: POSIX :: Linux
Classifier: Programming Language :: Python :: 3
Classifier: Programming Language :: Python :: 3.7
Classifier: Programming Language :: Python :: 3.8
Classifier: Programming Language :: Python :: 3.9
Provides-Extra: comet
Provides-Extra: netron
Requires-Dist: comet_ml (>=3.1.3,<4.0.0); extra == "comet"
Requires-Dist: netron (>=4.5,<6.0); extra == "netron"
Requires-Dist: numpy (>=1.17,<2.0)
Requires-Dist: pandas (>=1.0,<2.0)
Requires-Dist: scikit-learn (>=0.23,<0.25)
Requires-Dist: tensorboard (>=2.1,<3.0)
Requires-Dist: tqdm (>=4.41,<5.0)
Project-URL: Repository, https://github.com/khirotaka/enchanter
